admin_menu/__init__.py
admin_menu/sass/admin-menu.scss
admin_menu/templates/admin/base_site.html
admin_menu/templatetags/__init__.py
admin_menu/templatetags/custom_admin_css.py
admin_menu/templatetags/custom_admin_logo.py
admin_menu/templatetags/custom_admin_menu.py
django_admin_menu-1.6.dist-info/LICENSE
django_admin_menu-1.6.dist-info/METADATA
django_admin_menu-1.6.dist-info/WHEEL
django_admin_menu-1.6.dist-info/top_level.txt
django_admin_menu-1.6.dist-info/RECORD
