Metadata-Version: 2.1
Name: django-admin-menu
Version: 1.6
Summary: A Django admin theme with a horizontal, tabbed navigation bar
Home-page: http://github.com/cdrx/django-admin-menu
Author: Chris Rose
License: MIT
Keywords: django,admin,theme,interface,menu,navigation
Platform: UNKNOWN
Classifier: Development Status :: 5 - Production/Stable
Classifier: Environment :: Web Environment
Classifier: Framework :: Django
Classifier: Intended Audience :: Developers
Classifier: Operating System :: OS Independent
Classifier: Programming Language :: Python
Classifier: Programming Language :: Python :: 3
Classifier: Programming Language :: Python :: 3.5
License-File: LICENSE
Requires-Dist: libsass (<=1.0,>=0.20)
